setup.py
django_test_utilities.egg-info/PKG-INFO
django_test_utilities.egg-info/SOURCES.txt
django_test_utilities.egg-info/dependency_links.txt
django_test_utilities.egg-info/requires.txt
django_test_utilities.egg-info/top_level.txt
test_utilities/__init__.py
test_utilities/tests.py