Metadata-Version: 1.1
Name: django-test-utilities
Version: 0.5.2
Summary: Additional test functionality useful within Django
Home-page: https://github.com/jsatt/django-test-utilities
Author: Jeremy Satterfield
Author-email: jsatt0@gmail.com
License: Apache License 2.0
Platform: UNKNOWN
Classifier: Development Status :: 4 - Beta
Classifier: Environment :: Plugins
Classifier: Framework :: Django
Classifier: Intended Audience :: Developers
Classifier: License :: OSI Approved :: Apache Software License
Classifier: Operating System :: OS Independent
Classifier: Programming Language :: Python
Classifier: Programming Language :: Python :: 2
Classifier: Programming Language :: Python :: 2.7
Classifier: Topic :: Software Development :: Libraries :: Python Modules
